safepass/__init__.py
safepass/__main__.py
safepass/analytics.py
safepass/context_processors.py
safepass/encryption.py
safepass/generator.py
safepass/manage.py
safepass/models.py
safepass/settings.py
safepass/urls.py
safepass/views.py
safepass/wsgi.py
safepass/migrations/0001_initial.py
safepass/migrations/0002_passwordhistory.py
safepass/migrations/0003_passwordcard_subcategory.py
safepass/migrations/__init__.py
safepass/static/css/styles.css
safepass/static/css/components/alerts.css
safepass/static/css/components/auth.css
safepass/static/css/components/buttons.css
safepass/static/css/components/cards.css
safepass/static/css/components/dashboard.css
safepass/static/css/components/forms.css
safepass/static/css/components/generator.css
safepass/static/css/components/help.css
safepass/static/css/components/import_export.css
safepass/static/css/components/layout.css
safepass/static/css/components/profile.css
safepass/static/css/components/sidebar.css
safepass/static/js/app.js
safepass/static/js/modules/auth.js
safepass/static/js/modules/card_form.js
safepass/static/js/modules/cards.js
safepass/static/js/modules/dashboard.js
safepass/static/js/modules/generator.js
safepass/static/js/modules/import_export.js
safepass/static/js/modules/password_edit.js
safepass/static/js/modules/profile.js
safepass/templates/base.html
safepass/templates/card_add.html
safepass/templates/cards.html
safepass/templates/dashboard.html
safepass/templates/generator.html
safepass/templates/help.html
safepass/templates/import_export.html
safepass/templates/index.html
safepass/templates/password_edit.html
safepass/templates/profile.html
safepass/templates/auth/login.html
safepass/templates/auth/register.html
safepass/templates/partials/sidebar.html
safepass_cli-1.2.4.dist-info/METADATA
safepass_cli-1.2.4.dist-info/WHEEL
safepass_cli-1.2.4.dist-info/entry_points.txt
safepass_cli-1.2.4.dist-info/top_level.txt
safepass_cli-1.2.4.dist-info/RECORD
