Metadata-Version: 2.4
Name: safepass-cli
Version: 1.2.4
Summary: Offline password manager with strong encryption
Home-page: https://github.com/barancll/safepass
Author: Baran Celal Tonyalı
Author-email: tonyalibarancelal@gmail.com
Classifier: Development Status :: 4 - Beta
Classifier: Intended Audience :: End Users/Desktop
Classifier: Topic :: Security
Classifier: License :: OSI Approved :: MIT License
Classifier: Programming Language :: Python :: 3
Classifier: Programming Language :: Python :: 3.10
Classifier: Programming Language :: Python :: 3.11
Classifier: Programming Language :: Python :: 3.12
Classifier: Programming Language :: Python :: 3.13
Requires-Python: >=3.10
Requires-Dist: Django<5.2,>=5.1
Requires-Dist: cryptography>=41.0.0
Requires-Dist: django-cors-headers>=4.7.0
Dynamic: author
Dynamic: author-email
Dynamic: classifier
Dynamic: description
Dynamic: description-content-type
Dynamic: home-page
Dynamic: requires-dist
Dynamic: requires-python
Dynamic: summary
